ekacare/__init__.py
ekacare/client.py
ekacare/abdm/__init__.py
ekacare/abdm/profile.py
ekacare/appointments/__init__.py
ekacare/appointments/appointments.py
ekacare/auth/__init__.py
ekacare/auth/auth.py
ekacare/doctor_clinic/__init__.py
ekacare/doctor_clinic/clinic_doctor.py
ekacare/patient/__init__.py
ekacare/patient/patient.py
ekacare/records/__init__.py
ekacare/records/records.py
ekacare/tools/__init__.py
ekacare/tools/files.py
ekacare/utils/__init__.py
ekacare/utils/constants-file.py
ekacare/utils/exceptions.py
ekacare/v2rx/__init__.py
ekacare/v2rx/v2rx.py
ekacare/vitals/__init__.py
ekacare/vitals/vitals.py
ekacare/webhooks/__init__.py
ekacare/webhooks/appointment.py
ekacare/webhooks/enums.py
tests/__init__.py
tests/test_client.py
ekacare-0.1.3.dist-info/METADATA
ekacare-0.1.3.dist-info/WHEEL
ekacare-0.1.3.dist-info/top_level.txt
ekacare-0.1.3.dist-info/RECORD
